{
    "status": "OK",
    "usage": "By accessing AlchemyAPI or using information generated by AlchemyAPI, you are agreeing to be bound by the AlchemyAPI Terms of Use: http://www.alchemyapi.com/company/terms.html",
    "url": "http://www.bbc.com/news/37962741",
    "totalTransactions": "4",
    "language": "english",
    "concepts": [
        {
            "text": "Islam",
            "relevance": "0.967182",
            "dbpedia": "http://dbpedia.org/resource/Islam",
            "freebase": "http://rdf.freebase.com/ns/m.0flw86",
            "opencyc": "http://sw.opencyc.org/concept/Mx4rvVjLJZwpEbGdrcN5Y29ycA"
        },
        {
            "text": "Pakistan",
            "relevance": "0.879038",
            "dbpedia": "http://dbpedia.org/resource/Pakistan",
            "ciaFactbook": "http://www4.wiwiss.fu-berlin.de/factbook/resource/Pakistan",
            "freebase": "http://rdf.freebase.com/ns/m.05sb1",
            "opencyc": "http://sw.opencyc.org/concept/Mx4rvVi2-ZwpEbGdrcN5Y29ycA",
            "yago": "http://yago-knowledge.org/resource/Pakistan"
        },
        {
            "text": "Nawaz Sharif",
            "relevance": "0.736268",
            "website": "http://www.pmln.com.pk/",
            "dbpedia": "http://dbpedia.org/resource/Nawaz_Sharif",
            "freebase": "http://rdf.freebase.com/ns/m.020t62",
            "yago": "http://yago-knowledge.org/resource/Nawaz_Sharif"
        },
        {
            "text": "Iran",
            "relevance": "0.571065",
            "geo": "32.0 53.0",
            "dbpedia": "http://dbpedia.org/resource/Iran",
            "ciaFactbook": "http://www4.wiwiss.fu-berlin.de/factbook/resource/Iran",
            "freebase": "http://rdf.freebase.com/ns/m.03shp",
            "opencyc": "http://sw.opencyc.org/concept/Mx4rvVj11JwpEbGdrcN5Y29ycA",
            "yago": "http://yago-knowledge.org/resource/Iran"
        },
        {
            "text": "Benazir Bhutto",
            "relevance": "0.537075",
            "website": "http://www.benazirbhutto.org",
            "dbpedia": "http://dbpedia.org/resource/Benazir_Bhutto",
            "freebase": "http://rdf.freebase.com/ns/m.01bhq8",
            "opencyc": "http://sw.opencyc.org/concept/Mx4rhLf0SCy8QdiUDdmT979NRw",
            "yago": "http://yago-knowledge.org/resource/Benazir_Bhutto"
        },
        {
            "text": "Sufism",
            "relevance": "0.534409",
            "dbpedia": "http://dbpedia.org/resource/Sufism",
            "freebase": "http://rdf.freebase.com/ns/m.06_wx"
        },
        {
            "text": "Punjab",
            "relevance": "0.509889",
            "website": "http://www.punjab.gov.pk",
            "dbpedia": "http://dbpedia.org/resource/Punjab_(Pakistan)",
            "yago": "http://yago-knowledge.org/resource/Punjab_(Pakistan)"
        },
        {
            "text": "Mysticism",
            "relevance": "0.504073",
            "dbpedia": "http://dbpedia.org/resource/Mysticism",
            "freebase": "http://rdf.freebase.com/ns/m.0972s"
        },
        {
            "text": "Imran Khan",
            "relevance": "0.445696",
            "dbpedia": "http://dbpedia.org/resource/Imran_Khan",
            "freebase": "http://rdf.freebase.com/ns/m.025cj4",
            "yago": "http://yago-knowledge.org/resource/Imran_Khan"
        },
        {
            "text": "Sindh",
            "relevance": "0.436842",
            "website": "http://www.sindh.gov.pk",
            "dbpedia": "http://dbpedia.org/resource/Sindh",
            "freebase": "http://rdf.freebase.com/ns/m.075mb",
            "yago": "http://yago-knowledge.org/resource/Sindh"
        },
        {
            "text": "Karachi",
            "relevance": "0.426221",
            "website": "http://www.karachicity.gov.pk",
            "dbpedia": "http://dbpedia.org/resource/Karachi",
            "freebase": "http://rdf.freebase.com/ns/m.04cjn",
            "yago": "http://yago-knowledge.org/resource/Karachi",
            "geonames": "http://sws.geonames.org/1174872/"
        },
        {
            "text": "Pervez Musharraf",
            "relevance": "0.410749",
            "website": "http://www.generalpervaizmusharraf.com/PresidentialSpeeches.aspx",
            "dbpedia": "http://dbpedia.org/resource/Pervez_Musharraf",
            "freebase": "http://rdf.freebase.com/ns/m.061s_",
            "opencyc": "http://sw.opencyc.org/concept/Mx4rS0ynnBxbQdiQ_aQSrGYS2Q",
            "yago": "http://yago-knowledge.org/resource/Pervez_Musharraf"
        },
        {
            "text": "Balochistan",
            "relevance": "0.407867",
            "website": "http://www.balochistan.gov.pk",
            "dbpedia": "http://dbpedia.org/resource/Balochistan_(Pakistan)",
            "yago": "http://yago-knowledge.org/resource/Balochistan_(Pakistan)"
        },
        {
            "text": "Persian people",
            "relevance": "0.397636",
            "dbpedia": "http://dbpedia.org/resource/Persian_people",
            "freebase": "http://rdf.freebase.com/ns/m.064pj",
            "yago": "http://yago-knowledge.org/resource/Persian_people"
        },
        {
            "text": "Al-Ghazali",
            "relevance": "0.392735",
            "dbpedia": "http://dbpedia.org/resource/Al-Ghazali",
            "freebase": "http://rdf.freebase.com/ns/m.012prf",
            "yago": "http://yago-knowledge.org/resource/Al-Ghazali"
        },
        {
            "text": "Attack",
            "relevance": "0.388962",
            "dbpedia": "http://dbpedia.org/resource/Attack"
        },
        {
            "text": "President of Pakistan",
            "relevance": "0.384794",
            "website": "http://www.president.gov.pk",
            "dbpedia": "http://dbpedia.org/resource/President_of_Pakistan",
            "freebase": "http://rdf.freebase.com/ns/m.026776",
            "yago": "http://yago-knowledge.org/resource/President_of_Pakistan"
        },
        {
            "text": "South Asia",
            "relevance": "0.382719",
            "dbpedia": "http://dbpedia.org/resource/South_Asia",
            "freebase": "http://rdf.freebase.com/ns/m.06nn1",
            "yago": "http://yago-knowledge.org/resource/South_Asia"
        },
        {
            "text": "Qawwali",
            "relevance": "0.376113",
            "dbpedia": "http://dbpedia.org/resource/Qawwali",
            "freebase": "http://rdf.freebase.com/ns/m.02kp3s",
            "yago": "http://yago-knowledge.org/resource/Qawwali"
        },
        {
            "text": "Rumi",
            "relevance": "0.375218",
            "website": "http://www.mevlana.net/",
            "dbpedia": "http://dbpedia.org/resource/Rumi",
            "freebase": "http://rdf.freebase.com/ns/m.0461p"
        },
        {
            "text": "Extremism",
            "relevance": "0.374942",
            "dbpedia": "http://dbpedia.org/resource/Extremism",
            "freebase": "http://rdf.freebase.com/ns/m.027947",
            "opencyc": "http://sw.opencyc.org/concept/Mx4rtXcdrh6vQdiTK_zk8-3ZLg"
        },
        {
            "text": "Pashto language",
            "relevance": "0.37001",
            "dbpedia": "http://dbpedia.org/resource/Pashto_language",
            "freebase": "http://rdf.freebase.com/ns/m.0swlx",
            "opencyc": "http://sw.opencyc.org/concept/Mx4rvVjSTZwpEbGdrcN5Y29ycA",
            "yago": "http://yago-knowledge.org/resource/Pashto_language"
        },
        {
            "text": "Quetta",
            "relevance": "0.365781",
            "website": "http://www.quetta.gov.pk/",
            "dbpedia": "http://dbpedia.org/resource/Quetta",
            "freebase": "http://rdf.freebase.com/ns/m.0n84k",
            "yago": "http://yago-knowledge.org/resource/Quetta",
            "geonames": "http://sws.geonames.org/1167528/"
        },
        {
            "text": "Ali",
            "relevance": "0.364612",
            "dbpedia": "http://dbpedia.org/resource/Ali",
            "freebase": "http://rdf.freebase.com/ns/m.024c1p",
            "yago": "http://yago-knowledge.org/resource/Ali"
        },
        {
            "text": "Shia Islam",
            "relevance": "0.364196",
            "website": "http://www.theismaili.org/",
            "dbpedia": "http://dbpedia.org/resource/Shia_Islam",
            "freebase": "http://rdf.freebase.com/ns/m.06pq6",
            "opencyc": "http://sw.opencyc.org/concept/Mx4rvViP3ZwpEbGdrcN5Y29ycA"
        },
        {
            "text": "Afghan refugees",
            "relevance": "0.35526",
            "dbpedia": "http://dbpedia.org/resource/Afghan_refugees"
        },
        {
            "text": "Attack!",
            "relevance": "0.354837",
            "dbpedia": "http://dbpedia.org/resource/Attack!_(board_game)",
            "freebase": "http://rdf.freebase.com/ns/m.05p6q8"
        },
        {
            "text": "Pashtun people",
            "relevance": "0.344185",
            "dbpedia": "http://dbpedia.org/resource/Pashtun_people",
            "freebase": "http://rdf.freebase.com/ns/m.09743"
        },
        {
            "text": "Meditation",
            "relevance": "0.327974",
            "dbpedia": "http://dbpedia.org/resource/Meditation",
            "freebase": "http://rdf.freebase.com/ns/m.0517l",
            "opencyc": "http://sw.opencyc.org/concept/Mx4rvewF8JwpEbGdrcN5Y29ycA"
        }
    ],
    "entities": [
        {
            "type": "Facility",
            "relevance": "0.950359",
            "count": "2",
            "text": "Shah Noorani shrine"
        },
        {
            "type": "Country",
            "relevance": "0.782708",
            "count": "2",
            "text": "Balochistan"
        },
        {
            "type": "City",
            "relevance": "0.633792",
            "count": "2",
            "text": "Karachi"
        },
        {
            "type": "Country",
            "relevance": "0.624425",
            "count": "2",
            "text": "Pakistan",
            "disambiguated": {
                "subType": [
                    "Location",
                    "GovernmentalJurisdiction"
                ],
                "name": "Pakistan",
                "dbpedia": "http://dbpedia.org/resource/Pakistan",
                "freebase": "http://rdf.freebase.com/ns/m.05sb1",
                "ciaFactbook": "http://www4.wiwiss.fu-berlin.de/factbook/resource/Pakistan",
                "opencyc": "http://sw.opencyc.org/concept/Mx4rvVi2-ZwpEbGdrcN5Y29ycA",
                "yago": "http://yago-knowledge.org/resource/Pakistan"
            }
        },
        {
            "type": "Person",
            "relevance": "0.551948",
            "count": "1",
            "text": "Prime Minister Nawaz Sharif"
        },
        {
            "type": "Person",
            "relevance": "0.494722",
            "count": "1",
            "text": "Imran Khan",
            "disambiguated": {
                "subType": [
                    "Athlete",
                    "Politician",
                    "CricketBowler",
                    "CricketPlayer"
                ],
                "name": "Imran Khan",
                "dbpedia": "http://dbpedia.org/resource/Imran_Khan",
                "freebase": "http://rdf.freebase.com/ns/m.025cj4",
                "yago": "http://yago-knowledge.org/resource/Imran_Khan"
            }
        },
        {
            "type": "Person",
            "relevance": "0.482121",
            "count": "1",
            "text": "Amjad Sabri"
        },
        {
            "type": "City",
            "relevance": "0.47256",
            "count": "1",
            "text": "Quetta",
            "disambiguated": {
                "subType": [
                ],
                "name": "Quetta",
                "website": "http://www.quetta.gov.pk/",
                "dbpedia": "http://dbpedia.org/resource/Quetta",
                "freebase": "http://rdf.freebase.com/ns/m.0n84k",
                "geonames": "http://sws.geonames.org/1167528/",
                "yago": "http://yago-knowledge.org/resource/Quetta"
            }
        },
        {
            "type": "FieldTerminology",
            "relevance": "0.461615",
            "count": "1",
            "text": "suicide bombers"
        },
        {
            "type": "Organization",
            "relevance": "0.447154",
            "count": "1",
            "text": "Edhi Foundation",
            "disambiguated": {
                "subType": [
                    "Non-ProfitOrganisation"
                ],
                "name": "Edhi Foundation",
                "website": "http://www.edhi.org/",
                "dbpedia": "http://dbpedia.org/resource/Edhi_Foundation",
                "freebase": "http://rdf.freebase.com/ns/m.05tvf5",
                "yago": "http://yago-knowledge.org/resource/Edhi_Foundation"
            }
        },
        {
            "type": "Country",
            "relevance": "0.431809",
            "count": "1",
            "text": "Iran",
            "disambiguated": {
                "name": "Iran",
                "geo": "32.0 53.0",
                "dbpedia": "http://dbpedia.org/resource/Iran",
                "freebase": "http://rdf.freebase.com/ns/m.03shp",
                "ciaFactbook": "http://www4.wiwiss.fu-berlin.de/factbook/resource/Iran",
                "opencyc": "http://sw.opencyc.org/concept/Mx4rvVj11JwpEbGdrcN5Y29ycA",
                "yago": "http://yago-knowledge.org/resource/Iran"
            }
        },
        {
            "type": "FieldTerminology",
            "relevance": "0.42133",
            "count": "1",
            "text": "Emergency services"
        },
        {
            "type": "City",
            "relevance": "0.414884",
            "count": "1",
            "text": "Kuzdar"
        },
        {
            "type": "Person",
            "relevance": "0.407541",
            "count": "1",
            "text": "Charles Haviland"
        },
        {
            "type": "Company",
            "relevance": "0.401718",
            "count": "1",
            "text": "BBC",
            "disambiguated": {
                "subType": [
                    "MusicalAlbum",
                    "Broadcast",
                    "PeriodicalPublisher",
                    "ProductionCompany",
                    "TVNetwork",
                    "AwardNominee",
                    "AwardWinner",
                    "FilmDirector",
                    "FilmProducer",
                    "MusicalArtist",
                    "TVProducer"
                ],
                "name": "BBC",
                "website": "http://www.bbc.co.uk",
                "dbpedia": "http://dbpedia.org/resource/BBC",
                "freebase": "http://rdf.freebase.com/ns/m.0g5lhl7",
                "opencyc": "http://sw.opencyc.org/concept/Mx4rwMl8FpwpEbGdrcN5Y29ycA",
                "yago": "http://yago-knowledge.org/resource/BBC",
                "crunchbase": "http://www.crunchbase.com/company/bbc"
            }
        },
        {
            "type": "Quantity",
            "relevance": "0.401718",
            "count": "1",
            "text": "62 miles"
        },
        {
            "type": "Quantity",
            "relevance": "0.401718",
            "count": "1",
            "text": "100km"
        }
    ],
    "relations": [
        {
            "sentence": "An explosion at a remote Sufi Muslim shrine in the Pakistani region of Balochistan has killed 52 people and injured more than 100, officials say.",
            "subject": {
                "text": "officials"
            },
            "action": {
                "text": "say",
                "lemmatized": "say",
                "verb": {
                    "text": "say",
                    "tense": "present"
                }
            },
            "object": {
                "text": "An explosion at a remote Sufi Muslim shrine in the Pakistani region of Balochistan has killed 52 people and injured more than 100",
                "entities": [
                    {
                        "type": "Country",
                        "text": "Balochistan"
                    }
                ]
            }
        },
        {
            "sentence": " Emergency services struggled to reach the Shah Noorani shrine in Kuzdar.",
            "subject": {
                "text": "Emergency services",
                "entities": [
                    {
                        "type": "FieldTerminology",
                        "text": "Emergency services"
                    }
                ]
            },
            "action": {
                "text": "struggled",
                "lemmatized": "struggle",
                "verb": {
                    "text": "struggle",
                    "tense": "past"
                }
            },
            "object": {
                "text": "to reach the Shah Noorani shrine in Kuzdar",
                "entities": [
                    {
                        "type": "Facility",
                        "text": "Shah Noorani shrine"
                    },
                    {
                        "type": "City",
                        "text": "Kuzdar"
                    }
                ]
            }
        },
        {
            "sentence": " Emergency services struggled to reach the Shah Noorani shrine in Kuzdar.",
            "subject": {
                "text": "Emergency services",
                "entities": [
                    {
                        "type": "FieldTerminology",
                        "text": "Emergency services"
                    }
                ]
            },
            "action": {
                "text": "struggled to reach",
                "lemmatized": "struggle to reach",
                "verb": {
                    "text": "reach",
                    "tense": "future"
                }
            },
            "object": {
                "text": "the Shah Noorani shrine in Kuzdar",
                "entities": [
                    {
                        "type": "Facility",
                        "text": "Shah Noorani shrine"
                    },
                    {
                        "type": "City",
                        "text": "Kuzdar"
                    }
                ]
            }
        },
        {
            "sentence": " Worshippers were performing dhamal - a trance-like dance - when the bomb hit.",
            "subject": {
                "text": "Worshippers"
            },
            "action": {
                "text": "were",
                "lemmatized": "be",
                "verb": {
                    "text": "be",
                    "tense": "past"
                }
            },
            "object": {
                "text": "performing dhamal - a trance-like dance -"
            }
        },
        {
            "sentence": " Worshippers were performing dhamal - a trance-like dance - when the bomb hit.",
            "subject": {
                "text": "Worshippers"
            },
            "action": {
                "text": "were performing",
                "lemmatized": "be perform",
                "verb": {
                    "text": "perform",
                    "tense": "past"
                }
            },
            "object": {
                "text": "dhamal"
            }
        },
        {
            "sentence": " So-called Islamic State says one of its suicide bombers carried it out.",
            "subject": {
                "text": "So-called Islamic State"
            },
            "action": {
                "text": "says",
                "lemmatized": "say",
                "verb": {
                    "text": "say",
                    "tense": "present"
                }
            },
            "object": {
                "text": "one of its suicide bombers carried it out",
                "entities": [
                    {
                        "type": "FieldTerminology",
                        "text": "suicide bombers"
                    }
                ]
            }
        },
        {
            "sentence": " Sufism, a tolerant, mystical practice of Islam, has millions of followers in Pakistan but is opposed by extremists.",
            "subject": {
                "text": "Sufism, a tolerant, mystical practice of Islam,"
            },
            "action": {
                "text": "has",
                "lemmatized": "have",
                "verb": {
                    "text": "have",
                    "tense": "present"
                }
            },
            "object": {
                "text": "millions of followers"
            },
            "location": {
                "text": "in Pakistan",
                "entities": [
                    {
                        "type": "Country",
                        "text": "Pakistan",
                        "disambiguated": {
                            "subType": [
                                "Location",
                                "Country",
                                "GovernmentalJurisdiction"
                            ],
                            "name": "Pakistan",
                            "dbpedia": "http://dbpedia.org/resource/Pakistan",
                            "ciaFactbook": "http://www4.wiwiss.fu-berlin.de/factbook/resource/Pakistan",
                            "freebase": "http://rdf.freebase.com/ns/m.05sb1",
                            "opencyc": "http://sw.opencyc.org/concept/Mx4rvVi2-ZwpEbGdrcN5Y29ycA",
                            "yago": "http://yago-knowledge.org/resource/Pakistan"
                        }
                    }
                ]
            }
        },
        {
            "sentence": " Sufism, a tolerant, mystical practice of Islam, has millions of followers in Pakistan but is opposed by extremists.",
            "subject": {
                "text": "Sufism, a tolerant, mystical practice of Islam,"
            },
            "action": {
                "text": "is opposed",
                "lemmatized": "be oppose",
                "verb": {
                    "text": "be",
                    "tense": "present"
                }
            },
            "object": {
                "text": "by extremists"
            }
        },
        {
            "sentence": " The shrine attracts Sufi devotees from all over the country, as well as neighbouring Iran.",
            "subject": {
                "text": "Sufi devotees"
            },
            "action": {
                "text": "neighbouring",
                "lemmatized": "neighbour",
                "verb": {
                    "text": "neighbour",
                    "tense": "present"
                }
            },
            "object": {
                "text": "Iran",
                "entities": [
                    {
                        "type": "Country",
                        "text": "Iran",
                        "disambiguated": {
                            "name": "Iran",
                            "geo": "32.0 53.0",
                            "dbpedia": "http://dbpedia.org/resource/Iran",
                            "ciaFactbook": "http://www4.wiwiss.fu-berlin.de/factbook/resource/Iran",
                            "freebase": "http://rdf.freebase.com/ns/m.03shp",
                            "opencyc": "http://sw.opencyc.org/concept/Mx4rvVj11JwpEbGdrcN5Y29ycA",
                            "yago": "http://yago-knowledge.org/resource/Iran"
                        }
                    }
                ]
            }
        },
        {
            "sentence": " Officials say the bomb blast took place while hundreds of worshippers were present, taking part in the dhamal, which is staged every sunset.",
            "subject": {
                "text": "Officials"
            },
            "action": {
                "text": "say",
                "lemmatized": "say",
                "verb": {
                    "text": "say",
                    "tense": "present"
                }
            },
            "object": {
                "text": "the bomb blast took place while hundreds of worshippers were present, taking part in the dhamal, which is staged every sunset"
            }
        },
        {
            "sentence": " Because the shrine is in rough, hilly terrain, rescue efforts are difficult.",
            "subject": {
                "text": "the shrine",
                "entities": [
                    {
                        "type": "Facility",
                        "text": "Shah Noorani shrine"
                    }
                ]
            },
            "action": {
                "text": "is",
                "lemmatized": "be",
                "verb": {
                    "text": "be",
                    "tense": "present"
                }
            },
            "object": {
                "text": "in rough"
            }
        },
        {
            "sentence": " Because the shrine is in rough, hilly terrain, rescue efforts are difficult.",
            "subject": {
                "text": "rescue efforts"
            },
            "action": {
                "text": "are",
                "lemmatized": "be",
                "verb": {
                    "text": "be",
                    "tense": "present"
                }
            },
            "object": {
                "text": "difficult"
            }
        },
        {
            "sentence": " A renowned charity, the Edhi Foundation, says it has sent 50 ambulances which are now carrying people to hospitals in Karachi, 100km (62 miles) away, but officials say they need helicopters to save more lives.",
            "subject": {
                "text": "A renowned charity, the Edhi Foundation,",
                "entities": [
                    {
                        "type": "Organization",
                        "text": "Edhi Foundation",
                        "disambiguated": {
                            "subType": [
                                "Organization",
                                "Non-ProfitOrganisation"
                            ],
                            "name": "Edhi Foundation",
                            "website": "http://www.edhi.org/",
                            "dbpedia": "http://dbpedia.org/resource/Edhi_Foundation",
                            "freebase": "http://rdf.freebase.com/ns/m.05tvf5",
                            "yago": "http://yago-knowledge.org/resource/Edhi_Foundation"
                        }
                    }
                ]
            },
            "action": {
                "text": "says",
                "lemmatized": "say",
                "verb": {
                    "text": "say",
                    "tense": "present"
                }
            },
            "object": {
                "text": "it has sent 50 ambulances which are now carrying people to hospitals in Karachi, 100km (62 miles) away, but officials say they need helicopters to save more lives",
                "entities": [
                    {
                        "type": "City",
                        "text": "Karachi"
                    },
                    {
                        "type": "Quantity",
                        "text": "62 miles"
                    },
                    {
                        "type": "Quantity",
                        "text": "100km"
                    }
                ]
            }
        },
        {
            "sentence": " A renowned charity, the Edhi Foundation, says it has sent 50 ambulances which are now carrying people to hospitals in Karachi, 100km (62 miles) away, but officials say they need helicopters to save more lives.",
            "subject": {
                "text": "50 ambulances"
            },
            "action": {
                "text": "are",
                "lemmatized": "be",
                "verb": {
                    "text": "be",
                    "tense": "present"
                }
            },
            "object": {
                "text": "carrying people to hospitals in Karachi, 100km (62 miles)",
                "entities": [
                    {
                        "type": "City",
                        "text": "Karachi"
                    },
                    {
                        "type": "Quantity",
                        "text": "62 miles"
                    },
                    {
                        "type": "Quantity",
                        "text": "100km"
                    }
                ]
            }
        },
        {
            "sentence": " A renowned charity, the Edhi Foundation, says it has sent 50 ambulances which are now carrying people to hospitals in Karachi, 100km (62 miles) away, but officials say they need helicopters to save more lives.",
            "subject": {
                "text": "50 ambulances"
            },
            "action": {
                "text": "carrying",
                "lemmatized": "carry",
                "verb": {
                    "text": "carry",
                    "tense": "present"
                }
            },
            "object": {
                "text": "people to hospitals in Karachi, 100km (62 miles)",
                "entities": [
                    {
                        "type": "City",
                        "text": "Karachi"
                    },
                    {
                        "type": "Quantity",
                        "text": "62 miles"
                    },
                    {
                        "type": "Quantity",
                        "text": "100km"
                    }
                ]
            }
        },
        {
            "sentence": " A renowned charity, the Edhi Foundation, says it has sent 50 ambulances which are now carrying people to hospitals in Karachi, 100km (62 miles) away, but officials say they need helicopters to save more lives.",
            "subject": {
                "text": "they"
            },
            "action": {
                "text": "to save",
                "lemmatized": "to save",
                "verb": {
                    "text": "save",
                    "tense": "future"
                }
            },
            "object": {
                "text": "more lives"
            }
        },
        {
            "sentence": " Pakistani Prime Minister Nawaz Sharif condemned the attack and called for speedy rescue efforts.",
            "subject": {
                "text": "Pakistani Prime Minister Nawaz Sharif",
                "entities": [
                    {
                        "type": "Person",
                        "text": "Prime Minister Nawaz Sharif"
                    }
                ]
            },
            "action": {
                "text": "condemned",
                "lemmatized": "condemn",
                "verb": {
                    "text": "condemn",
                    "tense": "past"
                }
            },
            "object": {
                "text": "the attack and called for speedy rescue efforts"
            }
        },
        {
            "sentence": " Imran Khan, former cricketer and head of the Tehreek-e-Insaf party, said the attack had targeted the \"core of our society\".",
            "subject": {
                "text": "Imran Khan, former cricketer and head of the Tehreek-e-Insaf party,",
                "entities": [
                    {
                        "type": "Person",
                        "text": "Imran Khan",
                        "disambiguated": {
                            "subType": [
                                "Person",
                                "Athlete",
                                "Politician",
                                "CricketBowler",
                                "CricketPlayer"
                            ],
                            "name": "Imran Khan",
                            "dbpedia": "http://dbpedia.org/resource/Imran_Khan",
                            "freebase": "http://rdf.freebase.com/ns/m.025cj4",
                            "yago": "http://yago-knowledge.org/resource/Imran_Khan"
                        }
                    }
                ]
            },
            "action": {
                "text": "said",
                "lemmatized": "say",
                "verb": {
                    "text": "say",
                    "tense": "past"
                }
            },
            "object": {
                "text": "the attack had targeted the \"core of our society\""
            }
        },
        {
            "sentence": " The BBC's Charles Haviland says that because Sufism includes music and dance and reverence for saints, religious zealots often target its sites in Pakistan.",
            "subject": {
                "text": "The BBC's Charles Haviland",
                "entities": [
                    {
                        "type": "Company",
                        "text": "BBC",
                        "disambiguated": {
                            "subType": [
                                "Organization",
                                "MusicalAlbum",
                                "Broadcast",
                                "Company",
                                "PeriodicalPublisher",
                                "ProductionCompany",
                                "TVNetwork",
                                "AwardNominee",
                                "AwardWinner",
                                "FilmDirector",
                                "FilmProducer",
                                "MusicalArtist",
                                "TVProducer"
                            ],
                            "name": "BBC",
                            "website": "http://www.bbc.co.uk",
                            "dbpedia": "http://dbpedia.org/resource/BBC",
                            "freebase": "http://rdf.freebase.com/ns/m.0g5lhl7",
                            "opencyc": "http://sw.opencyc.org/concept/Mx4rwMl8FpwpEbGdrcN5Y29ycA",
                            "yago": "http://yago-knowledge.org/resource/BBC"
                        }
                    },
                    {
                        "type": "Person",
                        "text": "Charles Haviland"
                    }
                ]
            },
            "action": {
                "text": "says",
                "lemmatized": "say",
                "verb": {
                    "text": "say",
                    "tense": "present"
                }
            },
            "object": {
                "text": "that because Sufism includes music and dance and reverence for saints, religious zealots often target its sites in Pakistan",
                "entities": [
                    {
                        "type": "Country",
                        "text": "Pakistan",
                        "disambiguated": {
                            "subType": [
                                "Location",
                                "Country",
                                "GovernmentalJurisdiction"
                            ],
                            "name": "Pakistan",
                            "dbpedia": "http://dbpedia.org/resource/Pakistan",
                            "ciaFactbook": "http://www4.wiwiss.fu-berlin.de/factbook/resource/Pakistan",
                            "freebase": "http://rdf.freebase.com/ns/m.05sb1",
                            "opencyc": "http://sw.opencyc.org/concept/Mx4rvVi2-ZwpEbGdrcN5Y29ycA",
                            "yago": "http://yago-knowledge.org/resource/Pakistan"
                        }
                    }
                ]
            }
        },
        {
            "sentence": " The BBC's Charles Haviland says that because Sufism includes music and dance and reverence for saints, religious zealots often target its sites in Pakistan.",
            "subject": {
                "text": "music and dance and reverence for saints, religious zealots often target its sites in Pakistan",
                "entities": [
                    {
                        "type": "Country",
                        "text": "Pakistan",
                        "disambiguated": {
                            "subType": [
                                "Location",
                                "Country",
                                "GovernmentalJurisdiction"
                            ],
                            "name": "Pakistan",
                            "dbpedia": "http://dbpedia.org/resource/Pakistan",
                            "ciaFactbook": "http://www4.wiwiss.fu-berlin.de/factbook/resource/Pakistan",
                            "freebase": "http://rdf.freebase.com/ns/m.05sb1",
                            "opencyc": "http://sw.opencyc.org/concept/Mx4rvVi2-ZwpEbGdrcN5Y29ycA",
                            "yago": "http://yago-knowledge.org/resource/Pakistan"
                        }
                    }
                ]
            },
            "action": {
                "text": "includes",
                "lemmatized": "include",
                "verb": {
                    "text": "include",
                    "tense": "present"
                }
            },
            "object": {
                "text": "Sufism"
            }
        },
        {
            "sentence": " The BBC's Charles Haviland says that because Sufism includes music and dance and reverence for saints, religious zealots often target its sites in Pakistan.",
            "subject": {
                "text": "religious zealots"
            },
            "action": {
                "text": "target",
                "lemmatized": "target",
                "verb": {
                    "text": "target",
                    "tense": "present"
                }
            },
            "object": {
                "text": "its sites"
            },
            "location": {
                "text": "in Pakistan",
                "entities": [
                    {
                        "type": "Country",
                        "text": "Pakistan",
                        "disambiguated": {
                            "subType": [
                                "Location",
                                "Country",
                                "GovernmentalJurisdiction"
                            ],
                            "name": "Pakistan",
                            "dbpedia": "http://dbpedia.org/resource/Pakistan",
                            "ciaFactbook": "http://www4.wiwiss.fu-berlin.de/factbook/resource/Pakistan",
                            "freebase": "http://rdf.freebase.com/ns/m.05sb1",
                            "opencyc": "http://sw.opencyc.org/concept/Mx4rvVi2-ZwpEbGdrcN5Y29ycA",
                            "yago": "http://yago-knowledge.org/resource/Pakistan"
                        }
                    }
                ]
            }
        },
        {
            "sentence": " In June a famous Sufi singer, Amjad Sabri, was assassinated by two gunmen in Karachi.",
            "subject": {
                "text": "a famous Sufi singer, Amjad Sabri,",
                "entities": [
                    {
                        "type": "Person",
                        "text": "Amjad Sabri"
                    }
                ]
            },
            "action": {
                "text": "was",
                "lemmatized": "be",
                "verb": {
                    "text": "be",
                    "tense": "past"
                }
            },
            "object": {
                "text": "assassinated by two gunmen in Karachi",
                "entities": [
                    {
                        "type": "City",
                        "text": "Karachi"
                    }
                ]
            }
        },
        {
            "sentence": " In June a famous Sufi singer, Amjad Sabri, was assassinated by two gunmen in Karachi.",
            "subject": {
                "text": "by two gunmen"
            },
            "action": {
                "text": "was assassinated",
                "lemmatized": "be assassinate",
                "verb": {
                    "text": "assassinate",
                    "tense": "past"
                }
            },
            "object": {
                "text": "a famous Sufi singer, Amjad Sabri,",
                "entities": [
                    {
                        "type": "Person",
                        "text": "Amjad Sabri"
                    }
                ]
            },
            "location": {
                "text": "in Karachi",
                "entities": [
                    {
                        "type": "City",
                        "text": "Karachi"
                    }
                ]
            }
        },
        {
            "sentence": " Extremist groups in the province of Balochistan have frequently targeted civilians this year.",
            "subject": {
                "text": "Extremist groups in the province of Balochistan",
                "entities": [
                    {
                        "type": "Country",
                        "text": "Balochistan"
                    }
                ]
            },
            "action": {
                "text": "have",
                "lemmatized": "have",
                "verb": {
                    "text": "have",
                    "tense": "present"
                }
            },
            "object": {
                "text": "frequently targeted civilians this year"
            }
        },
        {
            "sentence": " Extremist groups in the province of Balochistan have frequently targeted civilians this year.",
            "subject": {
                "text": "Balochistan",
                "entities": [
                    {
                        "type": "Country",
                        "text": "Balochistan"
                    }
                ]
            },
            "action": {
                "text": "targeted",
                "lemmatized": "target",
                "verb": {
                    "text": "target",
                    "tense": "past"
                }
            },
            "object": {
                "text": "civilians"
            }
        },
        {
            "sentence": " In October, dozens were killed in an attack on a police college in the city of Quetta and in August an attack on a hospital there killed 70 people.",
            "subject": {
                "text": "dozens"
            },
            "action": {
                "text": "were killed",
                "lemmatized": "be kill",
                "verb": {
                    "text": "kill",
                    "tense": "past"
                }
            },
            "location": {
                "text": "in an attack on a police college in the city of Quetta",
                "entities": [
                    {
                        "type": "City",
                        "text": "Quetta",
                        "disambiguated": {
                            "subType": [
                                "Location",
                                "CityTown"
                            ],
                            "name": "Quetta",
                            "website": "http://www.quetta.gov.pk/",
                            "dbpedia": "http://dbpedia.org/resource/Quetta",
                            "freebase": "http://rdf.freebase.com/ns/m.0n84k",
                            "yago": "http://yago-knowledge.org/resource/Quetta",
                            "geonames": "http://sws.geonames.org/1167528/"
                        }
                    }
                ]
            }
        },
        {
            "sentence": " But doubt has been cast over IS claims of previous attacks in the country.",
            "subject": {
                "text": "doubt"
            },
            "action": {
                "text": "been",
                "lemmatized": "be",
                "verb": {
                    "text": "be",
                    "tense": "past"
                }
            },
            "object": {
                "text": "cast over IS claims of previous attacks in the country"
            }
        }
    ]
}
